hs_bridge/FPGA_Execution/__init__.py
hs_bridge/FPGA_Execution/base_functions.py
hs_bridge/FPGA_Execution/fpga_compiler.py
hs_bridge/FPGA_Execution/fpga_controller.py
hs_bridge/__init__.py
hs_bridge/api.py
hs_bridge/compile_network.py
hs_bridge/config.py
hs_bridge/config.yaml
hs_bridge/network.py
hs_bridge/utils.py
hs_bridge/wrapped_dmadump/Makefile
hs_bridge/wrapped_dmadump/adxdma_dmadump.cpp
hs_bridge/wrapped_dmadump/adxdma_dmadump.h
hs_bridge/wrapped_dmadump/build/lib.linux-x86_64-3.10/dmadump.cpython-310-x86_64-linux-gnu.so
hs_bridge/wrapped_dmadump/build/temp.linux-x86_64-3.10/adxdma_dmadump.o
hs_bridge/wrapped_dmadump/build/temp.linux-x86_64-3.10/dmadump.o
hs_bridge/wrapped_dmadump/cmdline.cpp
hs_bridge/wrapped_dmadump/cmdline.h
hs_bridge/wrapped_dmadump/dmadump.cpp
hs_bridge/wrapped_dmadump/dmadump.cpython-310-x86_64-linux-gnu.so
hs_bridge/wrapped_dmadump/dmadump.pyx
hs_bridge/wrapped_dmadump/include/adxdma/bc/platform.h
hs_bridge/wrapped_dmadump/include/adxdma/bc/structs.h
hs_bridge/wrapped_dmadump/include/adxdma/bc/types.h
hs_bridge/wrapped_dmadump/include/adxdma/bc/version.h
hs_bridge/wrapped_dmadump/include/adxdma/bc.h
hs_bridge/wrapped_dmadump/include/adxdma/linuxinfo.h
hs_bridge/wrapped_dmadump/include/adxdma/platform.h
hs_bridge/wrapped_dmadump/include/adxdma/status.h
hs_bridge/wrapped_dmadump/include/adxdma/structs.h
hs_bridge/wrapped_dmadump/include/adxdma/types.h
hs_bridge/wrapped_dmadump/include/adxdma/version.h
hs_bridge/wrapped_dmadump/include/adxdma.h
hs_bridge/wrapped_dmadump/include/exappcmdline.h
hs_bridge/wrapped_dmadump/include/exappendian.h
hs_bridge/wrapped_dmadump/include/exappevent.h
hs_bridge/wrapped_dmadump/include/exappmessage.h
hs_bridge/wrapped_dmadump/include/exappnumparse.h
hs_bridge/wrapped_dmadump/include/exapptermlayout.h
hs_bridge/wrapped_dmadump/include/exappthread.h
hs_bridge/wrapped_dmadump/include/exapptime.h
hs_bridge/wrapped_dmadump/setup.py
hs_bridge-0.10.6.dist-info/WHEEL
hs_bridge-0.10.6.dist-info/METADATA
hs_bridge-0.10.6.dist-info/RECORD
